llama_index/retrievers/bm25/__init__.py
llama_index/retrievers/bm25/base.py
flying_delta_retrievers_bm25-0.1.0.dist-info/METADATA
flying_delta_retrievers_bm25-0.1.0.dist-info/WHEEL
flying_delta_retrievers_bm25-0.1.0.dist-info/RECORD
